ALine/__init__.py
ALine/color.py
ALine/error.py
ALine/func_trace.py
ALine/main.py
ALine-1.0.0.dist-info/LICENSE
ALine-1.0.0.dist-info/METADATA
ALine-1.0.0.dist-info/WHEEL
ALine-1.0.0.dist-info/top_level.txt
ALine-1.0.0.dist-info/RECORD
